canns_lib-0.7.0.dist-info/WHEEL
canns_lib-0.7.0.dist-info/METADATA
canns_lib-0.7.0.dist-info/RECORD
canns_lib-0.7.0.dist-info/licenses/LICENSE
canns_lib.libs/libgcc_s-7393e603.so.1
canns_lib/_version.py
canns_lib/canns_lib.cpython-311-aarch64-linux-musl.so
canns_lib/__init__.py
canns_lib/spatial/__init__.py
canns_lib/spatial/plotting_styles.py
canns_lib/ripser/__init__.py
