Metadata-Version: 2.4
Name: canns-lib
Version: 0.7.0
Classifier: Development Status :: 4 - Beta
Classifier: Intended Audience :: Developers
Classifier: Intended Audience :: Science/Research
Classifier: Operating System :: OS Independent
Classifier: Programming Language :: Python
Classifier: Programming Language :: Python :: 3
Classifier: Programming Language :: Python :: 3.11
Classifier: Programming Language :: Python :: 3.12
Classifier: Programming Language :: Python :: 3.13
Classifier: Programming Language :: Rust
Classifier: Topic :: Scientific/Engineering :: Mathematics
Classifier: Topic :: Scientific/Engineering :: Information Analysis
Classifier: Topic :: Scientific/Engineering :: Artificial Intelligence
Classifier: Typing :: Typed
Requires-Dist: numpy>=1.21.0
Requires-Dist: scipy>=1.7.0
Requires-Dist: scikit-learn>=1.0.0
Requires-Dist: psutil>=7.0.0
Requires-Dist: pytest>=6.0 ; extra == 'dev'
Requires-Dist: pytest-benchmark>=3.4.0 ; extra == 'dev'
Requires-Dist: matplotlib>=3.3.0 ; extra == 'dev'
Requires-Dist: persim>=0.3.0 ; extra == 'dev'
Requires-Dist: ripser>=0.6.12 ; extra == 'dev'
Requires-Dist: ratinabox>=1.6.0 ; extra == 'dev'
Provides-Extra: dev
License-File: LICENSE
Summary: High-performance computational acceleration library for CANNS, providing optimized implementations for topological data analysis and neural network computations
Home-Page: https://github.com/routhleck/canns-lib
Author-email: Sichao He <sichaohe@outlook.com>
License-Expression: Apache-2.0
Requires-Python: >=3.11, <4.0
Project-URL: Homepage, https://github.com/routhleck/canns-lib
Project-URL: Repository, https://github.com/routhleck/canns-lib
